{
  "kind": "discovery#restDescription",
  "name": "admob",
  "title": "AdMob API",
  "parameters": {
    "oauth_token": {
      "type": "string",
      "description": "OAuth 2.0 token for the current user.",
      "location": "query"
    },
    "$.xgafv": {
      "enum": [
        "1",
        "2"
      ],
      "description": "V1 error format.",
      "type": "string",
      "location": "query",
      "enumDescriptions": [
        "v1 error format",
        "v2 error format"
      ]
    },
    "access_token": {
      "location": "query",
      "description": "OAuth access token.",
      "type": "string"
    },
    "upload_protocol": {
      "description": "Upload protocol for media (e.g. \"raw\", \"multipart\").",
      "type": "string",
      "location": "query"
    },
    "prettyPrint": {
      "type": "boolean",
      "location": "query",
      "default": "true",
      "description": "Returns response with indentations and line breaks."
    },
    "alt": {
      "enum": [
        "json",
        "media",
        "proto"
      ],
      "type": "string",
      "enumDescriptions": [
        "Responses with Content-Type of application/json",
        "Media download with context-dependent Content-Type",
        "Responses with Content-Type of application/x-protobuf"
      ],
      "location": "query",
      "description": "Data format for response.",
      "default": "json"
    },
    "key": {
      "location": "query",
      "description": "API key. Your API key identifies your project and provides you with API access, quota, and reports. Required unless you provide an OAuth 2.0 token.",
      "type": "string"
    },
    "fields": {
      "description": "Selector specifying which fields to include in a partial response.",
      "location": "query",
      "type": "string"
    },
    "callback": {
      "description": "JSONP",
      "location": "query",
      "type": "string"
    },
    "quotaUser": {
      "description": "Available to use for quota purposes for server-side applications. Can be any arbitrary string assigned to a user, but should not exceed 40 characters.",
      "type": "string",
      "location": "query"
    },
    "uploadType": {
      "description": "Legacy upload protocol for media (e.g. \"media\", \"multipart\").",
      "type": "string",
      "location": "query"
    }
  },
  "version": "v1beta",
  "basePath": "",
  "auth": {
    "oauth2": {
      "scopes": {
        "https://www.googleapis.com/auth/admob.report": {
          "description": "See your AdMob data"
        },
        "https://www.googleapis.com/auth/admob.readonly": {
          "description": "See your AdMob data"
        }
      }
    }
  },
  "discoveryVersion": "v1",
  "icons": {
    "x32": "http://www.google.com/images/icons/product/search-32.gif",
    "x16": "http://www.google.com/images/icons/product/search-16.gif"
  },
  "version_module": true,
  "protocol": "rest",
  "mtlsRootUrl": "https://admob.mtls.googleapis.com/",
  "resources": {
    "accounts": {
      "resources": {
        "adUnits": {
          "methods": {
            "list": {
              "path": "v1beta/{+parent}/adUnits",
              "id": "admob.accounts.adUnits.list",
              "parameters": {
                "parent": {
                  "required": true,
                  "type": "string",
                  "pattern": "^accounts/[^/]+$",
                  "location": "path",
                  "description": "Required. Resource name of the account to list ad units for. Example: accounts/pub-9876543210987654"
                },
                "pageSize": {
                  "type": "integer",
                  "location": "query",
                  "format": "int32",
                  "description": "The maximum number of ad units to return. If unspecified or 0, at most 1000 ad units will be returned. The maximum value is 10,000; values above 10,000 will be coerced to 10,000."
                },
                "pageToken": {
                  "description": "The value returned by the last `ListAdUnitsResponse`; indicates that this is a continuation of a prior `ListAdUnits` call, and that the system should return the next page of data.",
                  "location": "query",
                  "type": "string"
                }
              },
              "flatPath": "v1beta/accounts/{accountsId}/adUnits",
              "parameterOrder": [
                "parent"
              ],
              "scopes": [
                "https://www.googleapis.com/auth/admob.readonly"
              ],
              "description": "List the ad units under the specified AdMob account.",
              "httpMethod": "GET",
              "response": {
                "$ref": "ListAdUnitsResponse"
              },
              "streamingType": "NONE"
            }
          }
        },
        "apps": {
          "methods": {
            "list": {
              "parameters": {
                "pageSize": {
                  "type": "integer",
                  "format": "int32",
                  "location": "query",
                  "description": "The maximum number of apps to return. If unspecified or 0, at most 1000 apps will be returned. The maximum value is 10,000; values above 10,000 will be coerced to 10,000."
                },
                "pageToken": {
                  "location": "query",
                  "type": "string",
                  "description": "The value returned by the last `ListAppsResponse`; indicates that this is a continuation of a prior `ListApps` call, and that the system should return the next page of data."
                },
                "parent": {
                  "description": "Required. Resource name of the account to list apps for. Example: accounts/pub-9876543210987654",
                  "type": "string",
                  "location": "path",
                  "pattern": "^accounts/[^/]+$",
                  "required": true
                }
              },
              "description": "List the apps under the specified AdMob account.",
              "path": "v1beta/{+parent}/apps",
              "streamingType": "NONE",
              "flatPath": "v1beta/accounts/{accountsId}/apps",
              "scopes": [
                "https://www.googleapis.com/auth/admob.readonly"
              ],
              "id": "admob.accounts.apps.list",
              "response": {
                "$ref": "ListAppsResponse"
              },
              "parameterOrder": [
                "parent"
              ],
              "httpMethod": "GET"
            }
          }
        },
        "mediationReport": {
          "methods": {
            "generate": {
              "parameters": {
                "parent": {
                  "type": "string",
                  "location": "path",
                  "pattern": "^accounts/[^/]+$",
                  "description": "Resource name of the account to generate the report for. Example: accounts/pub-9876543210987654",
                  "required": true
                }
              },
              "request": {
                "$ref": "GenerateMediationReportRequest"
              },
              "flatPath": "v1beta/accounts/{accountsId}/mediationReport:generate",
              "id": "admob.accounts.mediationReport.generate",
              "response": {
                "$ref": "GenerateMediationReportResponse"
              },
              "description": "Generates an AdMob Mediation report based on the provided report specification. Returns result of a server-side streaming RPC. The result is returned in a sequence of responses.",
              "httpMethod": "POST",
              "parameterOrder": [
                "parent"
              ],
              "path": "v1beta/{+parent}/mediationReport:generate",
              "streamingType": "SERVER_SIDE",
              "scopes": [
                "https://www.googleapis.com/auth/admob.readonly",
                "https://www.googleapis.com/auth/admob.report"
              ]
            }
          }
        },
        "networkReport": {
          "methods": {
            "generate": {
              "parameters": {
                "parent": {
                  "pattern": "^accounts/[^/]+$",
                  "description": "Resource name of the account to generate the report for. Example: accounts/pub-9876543210987654",
                  "required": true,
                  "type": "string",
                  "location": "path"
                }
              },
              "flatPath": "v1beta/accounts/{accountsId}/networkReport:generate",
              "httpMethod": "POST",
              "parameterOrder": [
                "parent"
              ],
              "id": "admob.accounts.networkReport.generate",
              "scopes": [
                "https://www.googleapis.com/auth/admob.readonly",
                "https://www.googleapis.com/auth/admob.report"
              ],
              "description": "Generates an AdMob Network report based on the provided report specification. Returns result of a server-side streaming RPC. The result is returned in a sequence of responses.",
              "response": {
                "$ref": "GenerateNetworkReportResponse"
              },
              "request": {
                "$ref": "GenerateNetworkReportRequest"
              },
              "streamingType": "SERVER_SIDE",
              "path": "v1beta/{+parent}/networkReport:generate"
            }
          }
        }
      },
      "methods": {
        "list": {
          "flatPath": "v1beta/accounts",
          "httpMethod": "GET",
          "description": "Lists the AdMob publisher account that was most recently signed in to from the AdMob UI. For more information, see https://support.google.com/admob/answer/10243672.",
          "response": {
            "$ref": "ListPublisherAccountsResponse"
          },
          "streamingType": "NONE",
          "parameterOrder": [],
          "scopes": [
            "https://www.googleapis.com/auth/admob.readonly",
            "https://www.googleapis.com/auth/admob.report"
          ],
          "parameters": {
            "pageSize": {
              "format": "int32",
              "location": "query",
              "description": "Maximum number of accounts to return.",
              "type": "integer"
            },
            "pageToken": {
              "type": "string",
              "location": "query",
              "description": "The value returned by the last `ListPublisherAccountsResponse`; indicates that this is a continuation of a prior `ListPublisherAccounts` call, and that the system should return the next page of data."
            }
          },
          "id": "admob.accounts.list",
          "path": "v1beta/accounts"
        },
        "get": {
          "flatPath": "v1beta/accounts/{accountsId}",
          "parameters": {
            "name": {
              "required": true,
              "type": "string",
              "description": "Resource name of the publisher account to retrieve. Example: accounts/pub-9876543210987654",
              "location": "path",
              "pattern": "^accounts/[^/]+$"
            }
          },
          "id": "admob.accounts.get",
          "scopes": [
            "https://www.googleapis.com/auth/admob.readonly",
            "https://www.googleapis.com/auth/admob.report"
          ],
          "streamingType": "NONE",
          "httpMethod": "GET",
          "parameterOrder": [
            "name"
          ],
          "description": "Gets information about the specified AdMob publisher account.",
          "path": "v1beta/{+name}",
          "response": {
            "$ref": "PublisherAccount"
          }
        }
      }
    }
  },
  "schemas": {
    "ReportFooter": {
      "description": "Groups data available after report generation, for example, warnings and row counts. Always sent as the last message in the stream response.",
      "id": "ReportFooter",
      "type": "object",
      "properties": {
        "warnings": {
          "description": "Warnings associated with generation of the report.",
          "type": "array",
          "items": {
            "$ref": "ReportWarning"
          }
        },
        "matchingRowCount": {
          "format": "int64",
          "type": "string",
          "description": "Total number of rows that matched the request. Warning: This count does NOT always match the number of rows in the response. Do not make that assumption when processing the response."
        }
      }
    },
    "ListAdUnitsResponse": {
      "id": "ListAdUnitsResponse",
      "properties": {
        "nextPageToken": {
          "description": "If not empty, indicates that there may be more ad units for the request; this value should be passed in a new `ListAdUnitsRequest`.",
          "type": "string"
        },
        "adUnits": {
          "items": {
            "$ref": "AdUnit"
          },
          "description": "The resulting ad units for the requested account.",
          "type": "array"
        }
      },
      "description": "Response for the ad units list request.",
      "type": "object"
    },
    "ReportRowDimensionValue": {
      "id": "ReportRowDimensionValue",
      "description": "Representation of a dimension value.",
      "properties": {
        "value": {
          "type": "string",
          "description": "Dimension value in the format specified in the report's spec Dimension enum."
        },
        "displayLabel": {
          "description": "The localized string representation of the value. If unspecified, the display label should be derived from the value.",
          "type": "string"
        }
      },
      "type": "object"
    },
    "ReportWarning": {
      "properties": {
        "description": {
          "type": "string",
          "description": "Describes the details of the warning message, in English."
        },
        "type": {
          "type": "string",
          "enumDescriptions": [
            "Default value for an unset field. Do not use.",
            "Some data in this report is aggregated based on a time zone different from the requested time zone. This could happen if a local time-zone report has the start time before the last time this time zone changed. The description field will contain the date of the last time zone change.",
            "There is an unusual delay in processing the source data for the requested date range. The report results might be less up to date than usual. AdMob is aware of the issue and is actively working to resolve it.",
            "Warnings that are exposed without a specific type. Useful when new warning types are added but the API is not changed yet.",
            "The currency being requested is not the account currency. The earning metrics will be based on the requested currency, and thus not a good estimation of the final payment anymore, due to the currency rate fluctuation."
          ],
          "description": "Type of the warning.",
          "enum": [
            "TYPE_UNSPECIFIED",
            "DATA_BEFORE_ACCOUNT_TIMEZONE_CHANGE",
            "DATA_DELAYED",
            "OTHER",
            "REPORT_CURRENCY_NOT_ACCOUNT_CURRENCY"
          ]
        }
      },
      "id": "ReportWarning",
      "type": "object",
      "description": "Warnings associated with generation of the report."
    },
    "PublisherAccount": {
      "id": "PublisherAccount",
      "type": "object",
      "description": "A publisher account contains information relevant to the use of this API, such as the time zone used for the reports.",
      "properties": {
        "reportingTimeZone": {
          "type": "string",
          "description": "The time zone that is used in reports that are generated for this account. The value is a time-zone ID as specified by the CLDR project, for example, \"America/Los_Angeles\"."
        },
        "currencyCode": {
          "type": "string",
          "description": "Currency code of the earning-related metrics, which is the 3-letter code defined in ISO 4217. The daily average rate is used for the currency conversion."
        },
        "publisherId": {
          "description": "The unique ID by which this publisher account can be identified in the API requests (for example, pub-1234567890).",
          "type": "string"
        },
        "name": {
          "description": "Resource name of this account. Format is accounts/{publisher_id}.",
          "type": "string"
        }
      }
    },
    "AppManualAppInfo": {
      "description": "Information provided for manual apps which are not linked to an application store (Example: Google Play, App Store).",
      "properties": {
        "displayName": {
          "description": "The display name of the app as shown in the AdMob UI, which is provided by the user. The maximum length allowed is 80 characters.",
          "type": "string"
        }
      },
      "id": "AppManualAppInfo",
      "type": "object"
    },
    "StringList": {
      "type": "object",
      "description": "List of string values.",
      "id": "StringList",
      "properties": {
        "values": {
          "items": {
            "type": "string"
          },
          "type": "array",
          "description": "The string values."
        }
      }
    },
    "GenerateNetworkReportRequest": {
      "id": "GenerateNetworkReportRequest",
      "description": "Request to generate an AdMob Network report.",
      "properties": {
        "reportSpec": {
          "description": "Network report specification.",
          "$ref": "NetworkReportSpec"
        }
      },
      "type": "object"
    },
    "AdUnit": {
      "description": "Describes an AdMob ad unit.",
      "properties": {
        "name": {
          "type": "string",
          "description": "Resource name for this ad unit. Format is accounts/{publisher_id}/adUnits/{ad_unit_id_fragment} Example: accounts/pub-9876543210987654/adUnits/0123456789"
        },
        "adFormat": {
          "description": "AdFormat of the ad unit. Possible values are as follows: \"BANNER\" - Banner ad format. \"BANNER_INTERSTITIAL\" - Legacy format that can be used as either banner or interstitial. This format can no longer be created but can be targeted by mediation groups. \"INTERSTITIAL\" - A full screen ad. Supported ad types are \"RICH_MEDIA\" and \"VIDEO\". \"NATIVE\" - Native ad format. \"REWARDED\" - An ad that, once viewed, gets a callback verifying the view so that a reward can be given to the user. Supported ad types are \"RICH_MEDIA\" (interactive) and video where video can not be excluded.",
          "type": "string"
        },
        "adTypes": {
          "description": "Ad media type supported by this ad unit. Possible values as follows: \"RICH_MEDIA\" - Text, image, and other non-video media. \"VIDEO\" - Video media.",
          "type": "array",
          "items": {
            "type": "string"
          }
        },
        "adUnitId": {
          "description": "The externally visible ID of the ad unit which can be used to integrate with the AdMob SDK. This is a read only property. Example: ca-app-pub-9876543210987654/0123456789",
          "type": "string"
        },
        "appId": {
          "type": "string",
          "description": "The externally visible ID of the app this ad unit is associated with. Example: ca-app-pub-9876543210987654~0123456789"
        },
        "displayName": {
          "description": "The display name of the ad unit as shown in the AdMob UI, which is provided by the user. The maximum length allowed is 80 characters.",
          "type": "string"
        }
      },
      "type": "object",
      "id": "AdUnit"
    },
    "AppLinkedAppInfo": {
      "properties": {
        "appStoreId": {
          "type": "string",
          "description": "The app store ID of the app; present if and only if the app is linked to an app store. If the app is added to the Google Play store, it will be the application ID of the app. For example: \"com.example.myapp\". See https://developer.android.com/studio/build/application-id. If the app is added to the Apple App Store, it will be app store ID. For example \"105169111\". Note that setting the app store id is considered an irreversible action. Once an app is linked, it cannot be unlinked."
        },
        "displayName": {
          "readOnly": true,
          "type": "string",
          "description": "Output only. Display name of the app as it appears in the app store. This is an output-only field, and may be empty if the app cannot be found in the store."
        }
      },
      "description": "Information from the app store if the app is linked to an app store.",
      "id": "AppLinkedAppInfo",
      "type": "object"
    },
    "ListPublisherAccountsResponse": {
      "description": "Response for the publisher account list request.",
      "type": "object",
      "id": "ListPublisherAccountsResponse",
      "properties": {
        "nextPageToken": {
          "description": "If not empty, indicates that there might be more accounts for the request; you must pass this value in a new `ListPublisherAccountsRequest`.",
          "type": "string"
        },
        "account": {
          "type": "array",
          "description": "Publisher that the client credentials can access.",
          "items": {
            "$ref": "PublisherAccount"
          }
        }
      }
    },
    "NetworkReportSpecDimensionFilter": {
      "id": "NetworkReportSpecDimensionFilter",
      "description": "Describes which report rows to match based on their dimension values.",
      "properties": {
        "dimension": {
          "enumDescriptions": [
            "Default value for an unset field. Do not use.",
            "A date in the YYYY-MM-DD format (for example, \"2018-12-21\"). Requests can specify at most one time dimension.",
            "A month in the YYYY-MM format (for example, \"2018-12\"). Requests can specify at most one time dimension.",
            "The date of the first day of a week in the YYYY-MM-DD format (for example, \"2018-12-21\"). Requests can specify at most one time dimension.",
            "The unique ID of the ad unit (for example, \"ca-app-pub-1234/1234\"). If AD_UNIT dimension is specified, then APP is included automatically.",
            "The unique ID of the mobile application (for example, \"ca-app-pub-1234~1234\").",
            "Type of the ad (for example, \"text\" or \"image\"), an ad delivery dimension. **Warning:** The dimension is incompatible with [AD_REQUESTS](#Metric.ENUM_VALUES.AD_REQUESTS), [MATCH_RATE](#Metric.ENUM_VALUES.MATCH_RATE) and [IMPRESSION_RPM](#Metric.ENUM_VALUES.IMPRESSION_RPM) metrics.",
            "CLDR country code of the place where the ad views/clicks occur (for example, \"US\" or \"FR\"). This is a geography dimension.",
            "Format of the ad unit (for example, \"banner\", \"native\"), an ad delivery dimension.",
            "Mobile OS platform of the app (for example, \"Android\" or \"iOS\")."
          ],
          "enum": [
            "DIMENSION_UNSPECIFIED",
            "DATE",
            "MONTH",
            "WEEK",
            "AD_UNIT",
            "APP",
            "AD_TYPE",
            "COUNTRY",
            "FORMAT",
            "PLATFORM"
          ],
          "type": "string",
          "description": "Applies the filter criterion to the specified dimension."
        },
        "matchesAny": {
          "description": "Matches a row if its value for the specified dimension is in one of the values specified in this condition.",
          "$ref": "StringList"
        }
      },
      "type": "object"
    },
    "LocalizationSettings": {
      "description": "Localization settings for reports, such as currency and language. It affects how metrics are calculated.",
      "id": "LocalizationSettings",
      "type": "object",
      "properties": {
        "currencyCode": {
          "description": "Currency code of the earning related metrics, which is the 3-letter code defined in ISO 4217. The daily average rate is used for the currency conversion. Defaults to the account currency code if unspecified.",
          "type": "string"
        },
        "languageCode": {
          "type": "string",
          "description": "Language used for any localized text, such as some dimension value display labels. The language tag defined in the IETF BCP47. Defaults to 'en-US' if unspecified."
        }
      }
    },
    "ReportRowMetricValue": {
      "properties": {
        "integerValue": {
          "format": "int64",
          "type": "string",
          "description": "Metric integer value."
        },
        "doubleValue": {
          "type": "number",
          "description": "Double precision (approximate) decimal values. Rates are from 0 to 1.",
          "format": "double"
        },
        "microsValue": {
          "description": "Amount in micros. One million is equivalent to one unit. Currency value is in the unit (USD, EUR or other) specified by the request. For example, $6.50 whould be represented as 6500000 micros.",
          "type": "string",
          "format": "int64"
        }
      },
      "description": "Representation of a metric value.",
      "type": "object",
      "id": "ReportRowMetricValue"
    },
    "Date": {
      "type": "object",
      "properties": {
        "day": {
          "description": "Day of a month. Must be from 1 to 31 and valid for the year and month, or 0 to specify a year by itself or a year and month where the day isn't significant.",
          "format": "int32",
          "type": "integer"
        },
        "month": {
          "format": "int32",
          "description": "Month of a year. Must be from 1 to 12, or 0 to specify a year without a month and day.",
          "type": "integer"
        },
        "year": {
          "type": "integer",
          "description": "Year of the date. Must be from 1 to 9999, or 0 to specify a date without a year.",
          "format": "int32"
        }
      },
      "id": "Date",
      "description": "Represents a whole or partial calendar date, such as a birthday. The time of day and time zone are either specified elsewhere or are insignificant. The date is relative to the Gregorian Calendar. This can represent one of the following: * A full date, with non-zero year, month, and day values * A month and day value, with a zero year, such as an anniversary * A year on its own, with zero month and day values * A year and month value, with a zero day, such as a credit card expiration date Related types are google.type.TimeOfDay and `google.protobuf.Timestamp`."
    },
    "GenerateMediationReportResponse": {
      "properties": {
        "footer": {
          "description": "Additional information about the generated report, such as warnings about the data.",
          "$ref": "ReportFooter"
        },
        "row": {
          "description": "Actual report data.",
          "$ref": "ReportRow"
        },
        "header": {
          "description": "Report generation settings that describes the report contents, such as the report date range and localization settings.",
          "$ref": "ReportHeader"
        }
      },
      "id": "GenerateMediationReportResponse",
      "description": "The streaming response for the AdMob Mediation report where the first response contains the report header, then a stream of row responses, and finally a footer as the last response message. For example: [{ \"header\": { \"date_range\": { \"start_date\": {\"year\": 2018, \"month\": 9, \"day\": 1}, \"end_date\": {\"year\": 2018, \"month\": 9, \"day\": 1} }, \"localization_settings\": { \"currency_code\": \"USD\", \"language_code\": \"en-US\" } } }, { \"row\": { \"dimension_values\": { \"DATE\": {\"value\": \"20180918\"}, \"APP\": { \"value\": \"ca-app-pub-8123415297019784~1001342552\", \"display_label\": \"My app name!\" } }, \"metric_values\": { \"ESTIMATED_EARNINGS\": {\"decimal_value\": \"1324746\"} } } }, { \"footer\": {\"matching_row_count\": 1} }]",
      "type": "object"
    },
    "ListAppsResponse": {
      "id": "ListAppsResponse",
      "properties": {
        "nextPageToken": {
          "type": "string",
          "description": "If not empty, indicates that there may be more apps for the request; this value should be passed in a new `ListAppsRequest`."
        },
        "apps": {
          "description": "The resulting apps for the requested account.",
          "items": {
            "$ref": "App"
          },
          "type": "array"
        }
      },
      "description": "Response for the apps list request.",
      "type": "object"
    },
    "DateRange": {
      "id": "DateRange",
      "type": "object",
      "properties": {
        "startDate": {
          "description": "Start date of the date range, inclusive. Must be less than or equal to the end date.",
          "$ref": "Date"
        },
        "endDate": {
          "$ref": "Date",
          "description": "End date of the date range, inclusive. Must be greater than or equal to the start date."
        }
      },
      "description": "Specification of a single date range. Both dates are inclusive."
    },
    "GenerateMediationReportRequest": {
      "id": "GenerateMediationReportRequest",
      "description": "Request to generate an AdMob Mediation report.",
      "properties": {
        "reportSpec": {
          "$ref": "MediationReportSpec",
          "description": "Network report specification."
        }
      },
      "type": "object"
    },
    "GenerateNetworkReportResponse": {
      "type": "object",
      "description": "The streaming response for the AdMob Network report where the first response contains the report header, then a stream of row responses, and finally a footer as the last response message. For example: [{ \"header\": { \"dateRange\": { \"startDate\": {\"year\": 2018, \"month\": 9, \"day\": 1}, \"endDate\": {\"year\": 2018, \"month\": 9, \"day\": 1} }, \"localizationSettings\": { \"currencyCode\": \"USD\", \"languageCode\": \"en-US\" } } }, { \"row\": { \"dimensionValues\": { \"DATE\": {\"value\": \"20180918\"}, \"APP\": { \"value\": \"ca-app-pub-8123415297019784~1001342552\", displayLabel: \"My app name!\" } }, \"metricValues\": { \"ESTIMATED_EARNINGS\": {\"microsValue\": 6500000} } } }, { \"footer\": {\"matchingRowCount\": 1} }]",
      "properties": {
        "header": {
          "description": "Report generation settings that describes the report contents, such as the report date range and localization settings.",
          "$ref": "ReportHeader"
        },
        "row": {
          "description": "Actual report data.",
          "$ref": "ReportRow"
        },
        "footer": {
          "description": "Additional information about the generated report, such as warnings about the data.",
          "$ref": "ReportFooter"
        }
      },
      "id": "GenerateNetworkReportResponse"
    },
    "ReportHeader": {
      "properties": {
        "reportingTimeZone": {
          "description": "The report time zone. The value is a time-zone ID as specified by the CLDR project, for example, \"America/Los_Angeles\".",
          "type": "string"
        },
        "localizationSettings": {
          "$ref": "LocalizationSettings",
          "description": "Localization settings of the report. This is identical to the settings in the report request."
        },
        "dateRange": {
          "description": "The date range for which the report is generated. This is identical to the range specified in the report request.",
          "$ref": "DateRange"
        }
      },
      "description": "Groups data helps to treat the generated report. Always sent as a first message in the stream response.",
      "type": "object",
      "id": "ReportHeader"
    },
    "NetworkReportSpec": {
      "type": "object",
      "properties": {
        "maxReportRows": {
          "description": "Maximum number of report data rows to return. If the value is not set, the API returns as many rows as possible, up to 100000. Acceptable values are 1-100000, inclusive. Values larger than 100000 return an error.",
          "type": "integer",
          "format": "int32"
        },
        "dimensionFilters": {
          "items": {
            "$ref": "NetworkReportSpecDimensionFilter"
          },
          "type": "array",
          "description": "Describes which report rows to match based on their dimension values."
        },
        "sortConditions": {
          "description": "Describes the sorting of report rows. The order of the condition in the list defines its precedence; the earlier the condition, the higher its precedence. If no sort conditions are specified, the row ordering is undefined.",
          "items": {
            "$ref": "NetworkReportSpecSortCondition"
          },
          "type": "array"
        },
        "metrics": {
          "description": "List of metrics of the report. A report must specify at least one metric.",
          "items": {
            "enumDescriptions": [
              "Default value for an unset field. Do not use.",
              "The number of ad requests. The value is an integer. **Warning:** The metric is incompatible with [AD_TYPE](#Dimension.ENUM_VALUES.AD_TYPE) dimension.",
              "The number of times a user clicks an ad. The value is an integer.",
              "The estimated earnings of the AdMob publisher. The currency unit (USD, EUR, or other) of the earning metrics are determined by the localization setting for currency. The amount is in micros. For example, $6.50 would be represented as 6500000.",
              "The total number of ads shown to users. The value is an integer.",
              "The ratio of clicks over impressions. The value is a double precision (approximate) decimal value.",
              "The estimated earnings per thousand ad impressions. The value is in micros. For example, $1.03 would be represented as 1030000. Equivalent to eCPM in the AdMob UI. **Warning:** The metric is incompatible with [AD_TYPE](#Dimension.ENUM_VALUES.AD_TYPE) dimension.",
              "The number of times ads are returned in response to a request. The value is an integer.",
              "The ratio of matched ad requests over the total ad requests. The value is a double precision (approximate) decimal value. **Warning:** The metric is incompatible with [AD_TYPE](#Dimension.ENUM_VALUES.AD_TYPE) dimension.",
              "The ratio of ads that are displayed over ads that are returned, defined as impressions / matched requests. The value is a double precision (approximate) decimal value."
            ],
            "type": "string",
            "enum": [
              "METRIC_UNSPECIFIED",
              "AD_REQUESTS",
              "CLICKS",
              "ESTIMATED_EARNINGS",
              "IMPRESSIONS",
              "IMPRESSION_CTR",
              "IMPRESSION_RPM",
              "MATCHED_REQUESTS",
              "MATCH_RATE",
              "SHOW_RATE"
            ]
          },
          "type": "array"
        },
        "timeZone": {
          "description": "A report time zone. Accepts an IANA TZ name values, such as \"America/Los_Angeles.\" If no time zone is defined, the account default takes effect. Check default value by the get account action. **Warning:** The \"America/Los_Angeles\" is the only supported value at the moment.",
          "type": "string"
        },
        "dimensions": {
          "description": "List of dimensions of the report. The value combination of these dimensions determines the row of the report. If no dimensions are specified, the report returns a single row of requested metrics for the entire account.",
          "type": "array",
          "items": {
            "enumDescriptions": [
              "Default value for an unset field. Do not use.",
              "A date in the YYYY-MM-DD format (for example, \"2018-12-21\"). Requests can specify at most one time dimension.",
              "A month in the YYYY-MM format (for example, \"2018-12\"). Requests can specify at most one time dimension.",
              "The date of the first day of a week in the YYYY-MM-DD format (for example, \"2018-12-21\"). Requests can specify at most one time dimension.",
              "The unique ID of the ad unit (for example, \"ca-app-pub-1234/1234\"). If AD_UNIT dimension is specified, then APP is included automatically.",
              "The unique ID of the mobile application (for example, \"ca-app-pub-1234~1234\").",
              "Type of the ad (for example, \"text\" or \"image\"), an ad delivery dimension. **Warning:** The dimension is incompatible with [AD_REQUESTS](#Metric.ENUM_VALUES.AD_REQUESTS), [MATCH_RATE](#Metric.ENUM_VALUES.MATCH_RATE) and [IMPRESSION_RPM](#Metric.ENUM_VALUES.IMPRESSION_RPM) metrics.",
              "CLDR country code of the place where the ad views/clicks occur (for example, \"US\" or \"FR\"). This is a geography dimension.",
              "Format of the ad unit (for example, \"banner\", \"native\"), an ad delivery dimension.",
              "Mobile OS platform of the app (for example, \"Android\" or \"iOS\")."
            ],
            "type": "string",
            "enum": [
              "DIMENSION_UNSPECIFIED",
              "DATE",
              "MONTH",
              "WEEK",
              "AD_UNIT",
              "APP",
              "AD_TYPE",
              "COUNTRY",
              "FORMAT",
              "PLATFORM"
            ]
          }
        },
        "dateRange": {
          "$ref": "DateRange",
          "description": "The date range for which the report is generated."
        },
        "localizationSettings": {
          "$ref": "LocalizationSettings",
          "description": "Localization settings of the report."
        }
      },
      "description": "The specification for generating an AdMob Network report. For example, the specification to get clicks and estimated earnings for only the 'US' and 'CN' countries can look like the following example: { 'date_range': { 'start_date': {'year': 2018, 'month': 9, 'day': 1}, 'end_date': {'year': 2018, 'month': 9, 'day': 30} }, 'dimensions': ['DATE', 'APP', 'COUNTRY'], 'metrics': ['CLICKS', 'ESTIMATED_EARNINGS'], 'dimension_filters': [ { 'dimension': 'COUNTRY', 'matches_any': {'values': [{'value': 'US', 'value': 'CN'}]} } ], 'sort_conditions': [ {'dimension':'APP', order: 'ASCENDING'}, {'metric':'CLICKS', order: 'DESCENDING'} ], 'localization_settings': { 'currency_code': 'USD', 'language_code': 'en-US' } } For a better understanding, you can treat the preceding specification like the following pseudo SQL: SELECT DATE, APP, COUNTRY, CLICKS, ESTIMATED_EARNINGS FROM NETWORK_REPORT WHERE DATE \u003e= '2018-09-01' AND DATE \u003c= '2018-09-30' AND COUNTRY IN ('US', 'CN') GROUP BY DATE, APP, COUNTRY ORDER BY APP ASC, CLICKS DESC;",
      "id": "NetworkReportSpec"
    },
    "MediationReportSpec": {
      "description": "The specification for generating an AdMob Mediation report. For example, the specification to get observed ECPM sliced by ad source and app for the 'US' and 'CN' countries can look like the following example: { \"date_range\": { \"start_date\": {\"year\": 2018, \"month\": 9, \"day\": 1}, \"end_date\": {\"year\": 2018, \"month\": 9, \"day\": 30} }, \"dimensions\": [\"AD_SOURCE\", \"APP\", \"COUNTRY\"], \"metrics\": [\"OBSERVED_ECPM\"], \"dimension_filters\": [ { \"dimension\": \"COUNTRY\", \"matches_any\": {\"values\": [{\"value\": \"US\", \"value\": \"CN\"}]} } ], \"sort_conditions\": [ {\"dimension\":\"APP\", order: \"ASCENDING\"} ], \"localization_settings\": { \"currency_code\": \"USD\", \"language_code\": \"en-US\" } } For a better understanding, you can treat the preceding specification like the following pseudo SQL: SELECT AD_SOURCE, APP, COUNTRY, OBSERVED_ECPM FROM MEDIATION_REPORT WHERE DATE \u003e= '2018-09-01' AND DATE \u003c= '2018-09-30' AND COUNTRY IN ('US', 'CN') GROUP BY AD_SOURCE, APP, COUNTRY ORDER BY APP ASC;",
      "id": "MediationReportSpec",
      "properties": {
        "dateRange": {
          "description": "The date range for which the report is generated.",
          "$ref": "DateRange"
        },
        "timeZone": {
          "description": "A report time zone. Accepts an IANA TZ name values, such as \"America/Los_Angeles.\" If no time zone is defined, the account default takes effect. Check default value by the get account action. **Warning:** The \"America/Los_Angeles\" is the only supported value at the moment.",
          "type": "string"
        },
        "localizationSettings": {
          "description": "Localization settings of the report.",
          "$ref": "LocalizationSettings"
        },
        "dimensions": {
          "items": {
            "type": "string",
            "enum": [
              "DIMENSION_UNSPECIFIED",
              "DATE",
              "MONTH",
              "WEEK",
              "AD_SOURCE",
              "AD_SOURCE_INSTANCE",
              "AD_UNIT",
              "APP",
              "MEDIATION_GROUP",
              "COUNTRY",
              "FORMAT",
              "PLATFORM"
            ],
            "enumDescriptions": [
              "Default value for an unset field. Do not use.",
              "A date in the YYYY-MM-DD format (for example, \"2018-12-21\"). Requests can specify at most one time dimension.",
              "A month in the YYYY-MM format (for example, \"2018-12\"). Requests can specify at most one time dimension.",
              "The date of the first day of a week in the YYYY-MM-DD format (for example, \"2018-12-21\"). Requests can specify at most one time dimension.",
              "The [unique ID of the ad source](/admob/api/v1/ad_sources) (for example, \"5450213213286189855\" and \"AdMob Network\" as label value).",
              "The unique ID of the ad source instance (for example, \"ca-app-pub-1234#5678\" and \"AdMob (default)\" as label value).",
              "The unique ID of the ad unit (for example, \"ca-app-pub-1234/8790\"). If AD_UNIT dimension is specified, then APP is included automatically.",
              "The unique ID of the mobile application (for example, \"ca-app-pub-1234~1234\").",
              "The unique ID of the mediation group (for example, \"ca-app-pub-1234:mg:1234\" and \"AdMob (default)\" as label value).",
              "CLDR country code of the place where the ad views/clicks occur (for example, \"US\" or \"FR\"). This is a geography dimension.",
              "Format of the ad unit (for example, \"banner\", \"native\"), an ad delivery dimension.",
              "Mobile OS platform of the app (for example, \"Android\" or \"iOS\")."
            ]
          },
          "description": "List of dimensions of the report. The value combination of these dimensions determines the row of the report. If no dimensions are specified, the report returns a single row of requested metrics for the entire account.",
          "type": "array"
        },
        "maxReportRows": {
          "description": "Maximum number of report data rows to return. If the value is not set, the API returns as many rows as possible, up to 100000. Acceptable values are 1-100000, inclusive. Values larger than 100000 return an error.",
          "type": "integer",
          "format": "int32"
        },
        "dimensionFilters": {
          "description": "Describes which report rows to match based on their dimension values.",
          "items": {
            "$ref": "MediationReportSpecDimensionFilter"
          },
          "type": "array"
        },
        "sortConditions": {
          "type": "array",
          "items": {
            "$ref": "MediationReportSpecSortCondition"
          },
          "description": "Describes the sorting of report rows. The order of the condition in the list defines its precedence; the earlier the condition, the higher its precedence. If no sort conditions are specified, the row ordering is undefined."
        },
        "metrics": {
          "description": "List of metrics of the report. A report must specify at least one metric.",
          "type": "array",
          "items": {
            "enumDescriptions": [
              "Default value for an unset field. Do not use.",
              "The number of requests. The value is an integer.",
              "The number of times a user clicks an ad. The value is an integer.",
              "The estimated earnings of the AdMob publisher. The currency unit (USD, EUR, or other) of the earning metrics are determined by the localization setting for currency. The amount is in micros. For example, $6.50 would be represented as 6500000. Estimated earnings per mediation group and per ad source instance level is supported dating back to October 20, 2019. Third-party estimated earnings will show 0 for dates prior to October 20, 2019.",
              "The total number of ads shown to users. The value is an integer.",
              "The ratio of clicks over impressions. The value is a double precision (approximate) decimal value.",
              "The number of times ads are returned in response to a request. The value is an integer.",
              "The ratio of matched ad requests over the total ad requests. The value is a double precision (approximate) decimal value.",
              "The third-party ad network's estimated average eCPM. The currency unit (USD, EUR, or other) of the earning metrics are determined by the localization setting for currency. The amount is in micros. For example, $2.30 would be represented as 2300000. The estimated average eCPM per mediation group and per ad source instance level is supported dating back to October 20, 2019. Third-party estimated average eCPM will show 0 for dates prior to October 20, 2019."
            ],
            "type": "string",
            "enum": [
              "METRIC_UNSPECIFIED",
              "AD_REQUESTS",
              "CLICKS",
              "ESTIMATED_EARNINGS",
              "IMPRESSIONS",
              "IMPRESSION_CTR",
              "MATCHED_REQUESTS",
              "MATCH_RATE",
              "OBSERVED_ECPM"
            ]
          }
        }
      },
      "type": "object"
    },
    "MediationReportSpecSortCondition": {
      "id": "MediationReportSpecSortCondition",
      "type": "object",
      "description": "Sorting direction to be applied on a dimension or a metric.",
      "properties": {
        "metric": {
          "type": "string",
          "enumDescriptions": [
            "Default value for an unset field. Do not use.",
            "The number of requests. The value is an integer.",
            "The number of times a user clicks an ad. The value is an integer.",
            "The estimated earnings of the AdMob publisher. The currency unit (USD, EUR, or other) of the earning metrics are determined by the localization setting for currency. The amount is in micros. For example, $6.50 would be represented as 6500000. Estimated earnings per mediation group and per ad source instance level is supported dating back to October 20, 2019. Third-party estimated earnings will show 0 for dates prior to October 20, 2019.",
            "The total number of ads shown to users. The value is an integer.",
            "The ratio of clicks over impressions. The value is a double precision (approximate) decimal value.",
            "The number of times ads are returned in response to a request. The value is an integer.",
            "The ratio of matched ad requests over the total ad requests. The value is a double precision (approximate) decimal value.",
            "The third-party ad network's estimated average eCPM. The currency unit (USD, EUR, or other) of the earning metrics are determined by the localization setting for currency. The amount is in micros. For example, $2.30 would be represented as 2300000. The estimated average eCPM per mediation group and per ad source instance level is supported dating back to October 20, 2019. Third-party estimated average eCPM will show 0 for dates prior to October 20, 2019."
          ],
          "enum": [
            "METRIC_UNSPECIFIED",
            "AD_REQUESTS",
            "CLICKS",
            "ESTIMATED_EARNINGS",
            "IMPRESSIONS",
            "IMPRESSION_CTR",
            "MATCHED_REQUESTS",
            "MATCH_RATE",
            "OBSERVED_ECPM"
          ],
          "description": "Sort by the specified metric."
        },
        "order": {
          "type": "string",
          "description": "Sorting order of the dimension or metric.",
          "enumDescriptions": [
            "Default value for an unset field. Do not use.",
            "Sort dimension value or metric value in ascending order.",
            "Sort dimension value or metric value in descending order."
          ],
          "enum": [
            "SORT_ORDER_UNSPECIFIED",
            "ASCENDING",
            "DESCENDING"
          ]
        },
        "dimension": {
          "enumDescriptions": [
            "Default value for an unset field. Do not use.",
            "A date in the YYYY-MM-DD format (for example, \"2018-12-21\"). Requests can specify at most one time dimension.",
            "A month in the YYYY-MM format (for example, \"2018-12\"). Requests can specify at most one time dimension.",
            "The date of the first day of a week in the YYYY-MM-DD format (for example, \"2018-12-21\"). Requests can specify at most one time dimension.",
            "The [unique ID of the ad source](/admob/api/v1/ad_sources) (for example, \"5450213213286189855\" and \"AdMob Network\" as label value).",
            "The unique ID of the ad source instance (for example, \"ca-app-pub-1234#5678\" and \"AdMob (default)\" as label value).",
            "The unique ID of the ad unit (for example, \"ca-app-pub-1234/8790\"). If AD_UNIT dimension is specified, then APP is included automatically.",
            "The unique ID of the mobile application (for example, \"ca-app-pub-1234~1234\").",
            "The unique ID of the mediation group (for example, \"ca-app-pub-1234:mg:1234\" and \"AdMob (default)\" as label value).",
            "CLDR country code of the place where the ad views/clicks occur (for example, \"US\" or \"FR\"). This is a geography dimension.",
            "Format of the ad unit (for example, \"banner\", \"native\"), an ad delivery dimension.",
            "Mobile OS platform of the app (for example, \"Android\" or \"iOS\")."
          ],
          "type": "string",
          "enum": [
            "DIMENSION_UNSPECIFIED",
            "DATE",
            "MONTH",
            "WEEK",
            "AD_SOURCE",
            "AD_SOURCE_INSTANCE",
            "AD_UNIT",
            "APP",
            "MEDIATION_GROUP",
            "COUNTRY",
            "FORMAT",
            "PLATFORM"
          ],
          "description": "Sort by the specified dimension."
        }
      }
    },
    "NetworkReportSpecSortCondition": {
      "type": "object",
      "id": "NetworkReportSpecSortCondition",
      "description": "Sorting direction to be applied on a dimension or a metric.",
      "properties": {
        "metric": {
          "enum": [
            "METRIC_UNSPECIFIED",
            "AD_REQUESTS",
            "CLICKS",
            "ESTIMATED_EARNINGS",
            "IMPRESSIONS",
            "IMPRESSION_CTR",
            "IMPRESSION_RPM",
            "MATCHED_REQUESTS",
            "MATCH_RATE",
            "SHOW_RATE"
          ],
          "description": "Sort by the specified metric.",
          "type": "string",
          "enumDescriptions": [
            "Default value for an unset field. Do not use.",
            "The number of ad requests. The value is an integer. **Warning:** The metric is incompatible with [AD_TYPE](#Dimension.ENUM_VALUES.AD_TYPE) dimension.",
            "The number of times a user clicks an ad. The value is an integer.",
            "The estimated earnings of the AdMob publisher. The currency unit (USD, EUR, or other) of the earning metrics are determined by the localization setting for currency. The amount is in micros. For example, $6.50 would be represented as 6500000.",
            "The total number of ads shown to users. The value is an integer.",
            "The ratio of clicks over impressions. The value is a double precision (approximate) decimal value.",
            "The estimated earnings per thousand ad impressions. The value is in micros. For example, $1.03 would be represented as 1030000. Equivalent to eCPM in the AdMob UI. **Warning:** The metric is incompatible with [AD_TYPE](#Dimension.ENUM_VALUES.AD_TYPE) dimension.",
            "The number of times ads are returned in response to a request. The value is an integer.",
            "The ratio of matched ad requests over the total ad requests. The value is a double precision (approximate) decimal value. **Warning:** The metric is incompatible with [AD_TYPE](#Dimension.ENUM_VALUES.AD_TYPE) dimension.",
            "The ratio of ads that are displayed over ads that are returned, defined as impressions / matched requests. The value is a double precision (approximate) decimal value."
          ]
        },
        "dimension": {
          "enumDescriptions": [
            "Default value for an unset field. Do not use.",
            "A date in the YYYY-MM-DD format (for example, \"2018-12-21\"). Requests can specify at most one time dimension.",
            "A month in the YYYY-MM format (for example, \"2018-12\"). Requests can specify at most one time dimension.",
            "The date of the first day of a week in the YYYY-MM-DD format (for example, \"2018-12-21\"). Requests can specify at most one time dimension.",
            "The unique ID of the ad unit (for example, \"ca-app-pub-1234/1234\"). If AD_UNIT dimension is specified, then APP is included automatically.",
            "The unique ID of the mobile application (for example, \"ca-app-pub-1234~1234\").",
            "Type of the ad (for example, \"text\" or \"image\"), an ad delivery dimension. **Warning:** The dimension is incompatible with [AD_REQUESTS](#Metric.ENUM_VALUES.AD_REQUESTS), [MATCH_RATE](#Metric.ENUM_VALUES.MATCH_RATE) and [IMPRESSION_RPM](#Metric.ENUM_VALUES.IMPRESSION_RPM) metrics.",
            "CLDR country code of the place where the ad views/clicks occur (for example, \"US\" or \"FR\"). This is a geography dimension.",
            "Format of the ad unit (for example, \"banner\", \"native\"), an ad delivery dimension.",
            "Mobile OS platform of the app (for example, \"Android\" or \"iOS\")."
          ],
          "enum": [
            "DIMENSION_UNSPECIFIED",
            "DATE",
            "MONTH",
            "WEEK",
            "AD_UNIT",
            "APP",
            "AD_TYPE",
            "COUNTRY",
            "FORMAT",
            "PLATFORM"
          ],
          "description": "Sort by the specified dimension.",
          "type": "string"
        },
        "order": {
          "type": "string",
          "description": "Sorting order of the dimension or metric.",
          "enum": [
            "SORT_ORDER_UNSPECIFIED",
            "ASCENDING",
            "DESCENDING"
          ],
          "enumDescriptions": [
            "Default value for an unset field. Do not use.",
            "Sort dimension value or metric value in ascending order.",
            "Sort dimension value or metric value in descending order."
          ]
        }
      }
    },
    "App": {
      "type": "object",
      "description": "Describes an AdMob app for a specific platform (For example: Android or iOS).",
      "id": "App",
      "properties": {
        "manualAppInfo": {
          "description": "The information for an app that is not linked to any app store. After an app is linked, this information is still retrivable. If no name is provided for the app upon creation, a placeholder name will be used.",
          "$ref": "AppManualAppInfo"
        },
        "linkedAppInfo": {
          "$ref": "AppLinkedAppInfo",
          "description": "Immutable. The information for an app that is linked to an app store. This field is present if and only if the app is linked to an app store."
        },
        "name": {
          "type": "string",
          "description": "Resource name for this app. Format is accounts/{publisher_id}/apps/{app_id_fragment} Example: accounts/pub-9876543210987654/apps/0123456789"
        },
        "appId": {
          "type": "string",
          "description": "The externally visible ID of the app which can be used to integrate with the AdMob SDK. This is a read only property. Example: ca-app-pub-9876543210987654~0123456789"
        },
        "platform": {
          "description": "Describes the platform of the app. Limited to \"IOS\" and \"ANDROID\".",
          "type": "string"
        }
      }
    },
    "MediationReportSpecDimensionFilter": {
      "properties": {
        "dimension": {
          "type": "string",
          "enumDescriptions": [
            "Default value for an unset field. Do not use.",
            "A date in the YYYY-MM-DD format (for example, \"2018-12-21\"). Requests can specify at most one time dimension.",
            "A month in the YYYY-MM format (for example, \"2018-12\"). Requests can specify at most one time dimension.",
            "The date of the first day of a week in the YYYY-MM-DD format (for example, \"2018-12-21\"). Requests can specify at most one time dimension.",
            "The [unique ID of the ad source](/admob/api/v1/ad_sources) (for example, \"5450213213286189855\" and \"AdMob Network\" as label value).",
            "The unique ID of the ad source instance (for example, \"ca-app-pub-1234#5678\" and \"AdMob (default)\" as label value).",
            "The unique ID of the ad unit (for example, \"ca-app-pub-1234/8790\"). If AD_UNIT dimension is specified, then APP is included automatically.",
            "The unique ID of the mobile application (for example, \"ca-app-pub-1234~1234\").",
            "The unique ID of the mediation group (for example, \"ca-app-pub-1234:mg:1234\" and \"AdMob (default)\" as label value).",
            "CLDR country code of the place where the ad views/clicks occur (for example, \"US\" or \"FR\"). This is a geography dimension.",
            "Format of the ad unit (for example, \"banner\", \"native\"), an ad delivery dimension.",
            "Mobile OS platform of the app (for example, \"Android\" or \"iOS\")."
          ],
          "enum": [
            "DIMENSION_UNSPECIFIED",
            "DATE",
            "MONTH",
            "WEEK",
            "AD_SOURCE",
            "AD_SOURCE_INSTANCE",
            "AD_UNIT",
            "APP",
            "MEDIATION_GROUP",
            "COUNTRY",
            "FORMAT",
            "PLATFORM"
          ],
          "description": "Applies the filter criterion to the specified dimension."
        },
        "matchesAny": {
          "$ref": "StringList",
          "description": "Matches a row if its value for the specified dimension is in one of the values specified in this condition."
        }
      },
      "description": "Describes which report rows to match based on their dimension values.",
      "type": "object",
      "id": "MediationReportSpecDimensionFilter"
    },
    "ReportRow": {
      "type": "object",
      "properties": {
        "metricValues": {
          "additionalProperties": {
            "$ref": "ReportRowMetricValue"
          },
          "description": "Map of metric values in a row, with keys as enum name of the metrics. If a metric being requested has no value returned, the map will not include it.",
          "type": "object"
        },
        "dimensionValues": {
          "type": "object",
          "description": "Map of dimension values in a row, with keys as enum name of the dimensions.",
          "additionalProperties": {
            "$ref": "ReportRowDimensionValue"
          }
        }
      },
      "description": "A row of the returning report.",
      "id": "ReportRow"
    }
  },
  "ownerDomain": "google.com",
  "baseUrl": "https://admob.googleapis.com/",
  "revision": "20210227",
  "rootUrl": "https://admob.googleapis.com/",
  "batchPath": "batch",
  "canonicalName": "AdMob",
  "documentationLink": "https://developers.google.com/admob/api/",
  "fullyEncodeReservedExpansion": true,
  "servicePath": "",
  "description": "The AdMob API allows publishers to programmatically get information about their AdMob account. ",
  "id": "admob:v1beta",
  "ownerName": "Google"
}
